{
  "id": "999877a9-a5ed-4dee-8a07-8a95d32a6bbc",
  "prevId": "00000000-0000-0000-0000-000000000000",
  "version": "7",
  "dialect": "postgresql",
  "tables": {
    "public.sample_payment_history": {
      "name": "sample_payment_history",
      "schema": "",
      "columns": {
        "id": {
          "name": "id",
          "type": "uuid",
          "primaryKey": true,
          "notNull": true,
          "default": "gen_random_uuid()"
        },
        "user_id": {
          "name": "user_id",
          "type": "uuid",
          "primaryKey": false,
          "notNull": true
        },
        "subscription_id": {
          "name": "subscription_id",
          "type": "uuid",
          "primaryKey": false,
          "notNull": false
        },
        "stripe_invoice_id": {
          "name": "stripe_invoice_id",
          "type": "varchar(255)",
          "primaryKey": false,
          "notNull": true
        },
        "stripe_payment_intent_id": {
          "name": "stripe_payment_intent_id",
          "type": "varchar(255)",
          "primaryKey": false,
          "notNull": false
        },
        "stripe_charge_id": {
          "name": "stripe_charge_id",
          "type": "varchar(255)",
          "primaryKey": false,
          "notNull": false
        },
        "amount": {
          "name": "amount",
          "type": "integer",
          "primaryKey": false,
          "notNull": true
        },
        "currency": {
          "name": "currency",
          "type": "varchar(10)",
          "primaryKey": false,
          "notNull": true,
          "default": "'jpy'"
        },
        "status": {
          "name": "status",
          "type": "sample_payment_status",
          "typeSchema": "public",
          "primaryKey": false,
          "notNull": true
        },
        "description": {
          "name": "description",
          "type": "text",
          "primaryKey": false,
          "notNull": false
        },
        "period_start": {
          "name": "period_start",
          "type": "timestamp",
          "primaryKey": false,
          "notNull": false
        },
        "period_end": {
          "name": "period_end",
          "type": "timestamp",
          "primaryKey": false,
          "notNull": false
        },
        "payment_method": {
          "name": "payment_method",
          "type": "varchar(50)",
          "primaryKey": false,
          "notNull": false
        },
        "last4": {
          "name": "last4",
          "type": "varchar(4)",
          "primaryKey": false,
          "notNull": false
        },
        "brand": {
          "name": "brand",
          "type": "varchar(20)",
          "primaryKey": false,
          "notNull": false
        },
        "refunded_amount": {
          "name": "refunded_amount",
          "type": "integer",
          "primaryKey": false,
          "notNull": false,
          "default": 0
        },
        "refunded_at": {
          "name": "refunded_at",
          "type": "timestamp",
          "primaryKey": false,
          "notNull": false
        },
        "refund_reason": {
          "name": "refund_reason",
          "type": "text",
          "primaryKey": false,
          "notNull": false
        },
        "paid_at": {
          "name": "paid_at",
          "type": "timestamp",
          "primaryKey": false,
          "notNull": false
        },
        "failed_at": {
          "name": "failed_at",
          "type": "timestamp",
          "primaryKey": false,
          "notNull": false
        },
        "created_at": {
          "name": "created_at",
          "type": "timestamp",
          "primaryKey": false,
          "notNull": true,
          "default": "now()"
        }
      },
      "indexes": {
        "sample_payment_history_user_id_idx": {
          "name": "sample_payment_history_user_id_idx",
          "columns": [
            {
              "expression": "user_id",
              "isExpression": false,
              "asc": true,
              "nulls": "last"
            }
          ],
          "isUnique": false,
          "concurrently": false,
          "method": "btree",
          "with": {}
        },
        "sample_payment_history_subscription_id_idx": {
          "name": "sample_payment_history_subscription_id_idx",
          "columns": [
            {
              "expression": "subscription_id",
              "isExpression": false,
              "asc": true,
              "nulls": "last"
            }
          ],
          "isUnique": false,
          "concurrently": false,
          "method": "btree",
          "with": {}
        },
        "sample_payment_history_status_idx": {
          "name": "sample_payment_history_status_idx",
          "columns": [
            {
              "expression": "status",
              "isExpression": false,
              "asc": true,
              "nulls": "last"
            }
          ],
          "isUnique": false,
          "concurrently": false,
          "method": "btree",
          "with": {}
        },
        "sample_payment_history_created_at_idx": {
          "name": "sample_payment_history_created_at_idx",
          "columns": [
            {
              "expression": "created_at",
              "isExpression": false,
              "asc": true,
              "nulls": "last"
            }
          ],
          "isUnique": false,
          "concurrently": false,
          "method": "btree",
          "with": {}
        }
      },
      "foreignKeys": {
        "sample_payment_history_subscription_id_sample_subscriptions_id_fk": {
          "name": "sample_payment_history_subscription_id_sample_subscriptions_id_fk",
          "tableFrom": "sample_payment_history",
          "tableTo": "sample_subscriptions",
          "columnsFrom": [
            "subscription_id"
          ],
          "columnsTo": [
            "id"
          ],
          "onDelete": "cascade",
          "onUpdate": "no action"
        }
      },
      "compositePrimaryKeys": {},
      "uniqueConstraints": {
        "sample_payment_history_stripe_invoice_id_unique": {
          "name": "sample_payment_history_stripe_invoice_id_unique",
          "nullsNotDistinct": false,
          "columns": [
            "stripe_invoice_id"
          ]
        }
      },
      "policies": {},
      "checkConstraints": {},
      "isRLSEnabled": false
    },
    "public.sample_plan_limits": {
      "name": "sample_plan_limits",
      "schema": "",
      "columns": {
        "id": {
          "name": "id",
          "type": "uuid",
          "primaryKey": true,
          "notNull": true,
          "default": "gen_random_uuid()"
        },
        "plan": {
          "name": "plan",
          "type": "sample_plan",
          "typeSchema": "public",
          "primaryKey": false,
          "notNull": true
        },
        "monthly_usage_limit": {
          "name": "monthly_usage_limit",
          "type": "integer",
          "primaryKey": false,
          "notNull": true
        },
        "projects_limit": {
          "name": "projects_limit",
          "type": "integer",
          "primaryKey": false,
          "notNull": true
        },
        "members_per_project_limit": {
          "name": "members_per_project_limit",
          "type": "integer",
          "primaryKey": false,
          "notNull": true
        },
        "features": {
          "name": "features",
          "type": "jsonb",
          "primaryKey": false,
          "notNull": true,
          "default": "'{}'::jsonb"
        },
        "monthly_price": {
          "name": "monthly_price",
          "type": "integer",
          "primaryKey": false,
          "notNull": true
        },
        "yearly_price": {
          "name": "yearly_price",
          "type": "integer",
          "primaryKey": false,
          "notNull": true
        },
        "display_order": {
          "name": "display_order",
          "type": "integer",
          "primaryKey": false,
          "notNull": true,
          "default": 0
        },
        "created_at": {
          "name": "created_at",
          "type": "timestamp",
          "primaryKey": false,
          "notNull": true,
          "default": "now()"
        },
        "updated_at": {
          "name": "updated_at",
          "type": "timestamp",
          "primaryKey": false,
          "notNull": true,
          "default": "now()"
        }
      },
      "indexes": {},
      "foreignKeys": {},
      "compositePrimaryKeys": {},
      "uniqueConstraints": {
        "sample_plan_limits_plan_unique": {
          "name": "sample_plan_limits_plan_unique",
          "nullsNotDistinct": false,
          "columns": [
            "plan"
          ]
        }
      },
      "policies": {},
      "checkConstraints": {},
      "isRLSEnabled": false
    },
    "public.sample_projects": {
      "name": "sample_projects",
      "schema": "",
      "columns": {
        "id": {
          "name": "id",
          "type": "uuid",
          "primaryKey": true,
          "notNull": true,
          "default": "gen_random_uuid()"
        },
        "user_id": {
          "name": "user_id",
          "type": "uuid",
          "primaryKey": false,
          "notNull": true
        },
        "name": {
          "name": "name",
          "type": "varchar(255)",
          "primaryKey": false,
          "notNull": true
        },
        "description": {
          "name": "description",
          "type": "text",
          "primaryKey": false,
          "notNull": false
        },
        "status": {
          "name": "status",
          "type": "sample_project_status",
          "typeSchema": "public",
          "primaryKey": false,
          "notNull": true,
          "default": "'active'"
        },
        "tags": {
          "name": "tags",
          "type": "jsonb",
          "primaryKey": false,
          "notNull": true,
          "default": "'[]'::jsonb"
        },
        "metadata": {
          "name": "metadata",
          "type": "jsonb",
          "primaryKey": false,
          "notNull": true,
          "default": "'{}'::jsonb"
        },
        "start_date": {
          "name": "start_date",
          "type": "timestamp",
          "primaryKey": false,
          "notNull": false
        },
        "end_date": {
          "name": "end_date",
          "type": "timestamp",
          "primaryKey": false,
          "notNull": false
        },
        "priority": {
          "name": "priority",
          "type": "integer",
          "primaryKey": false,
          "notNull": true,
          "default": 0
        },
        "progress": {
          "name": "progress",
          "type": "integer",
          "primaryKey": false,
          "notNull": true,
          "default": 0
        },
        "created_at": {
          "name": "created_at",
          "type": "timestamp",
          "primaryKey": false,
          "notNull": true,
          "default": "now()"
        },
        "updated_at": {
          "name": "updated_at",
          "type": "timestamp",
          "primaryKey": false,
          "notNull": true,
          "default": "now()"
        },
        "deleted_at": {
          "name": "deleted_at",
          "type": "timestamp",
          "primaryKey": false,
          "notNull": false
        }
      },
      "indexes": {
        "sample_projects_user_id_idx": {
          "name": "sample_projects_user_id_idx",
          "columns": [
            {
              "expression": "user_id",
              "isExpression": false,
              "asc": true,
              "nulls": "last"
            }
          ],
          "isUnique": false,
          "concurrently": false,
          "method": "btree",
          "with": {}
        },
        "sample_projects_status_idx": {
          "name": "sample_projects_status_idx",
          "columns": [
            {
              "expression": "status",
              "isExpression": false,
              "asc": true,
              "nulls": "last"
            }
          ],
          "isUnique": false,
          "concurrently": false,
          "method": "btree",
          "with": {}
        },
        "sample_projects_created_at_idx": {
          "name": "sample_projects_created_at_idx",
          "columns": [
            {
              "expression": "created_at",
              "isExpression": false,
              "asc": true,
              "nulls": "last"
            }
          ],
          "isUnique": false,
          "concurrently": false,
          "method": "btree",
          "with": {}
        }
      },
      "foreignKeys": {},
      "compositePrimaryKeys": {},
      "uniqueConstraints": {},
      "policies": {},
      "checkConstraints": {},
      "isRLSEnabled": false
    },
    "public.sample_subscriptions": {
      "name": "sample_subscriptions",
      "schema": "",
      "columns": {
        "id": {
          "name": "id",
          "type": "uuid",
          "primaryKey": true,
          "notNull": true,
          "default": "gen_random_uuid()"
        },
        "user_id": {
          "name": "user_id",
          "type": "uuid",
          "primaryKey": false,
          "notNull": true
        },
        "stripe_subscription_id": {
          "name": "stripe_subscription_id",
          "type": "varchar(255)",
          "primaryKey": false,
          "notNull": true
        },
        "stripe_price_id": {
          "name": "stripe_price_id",
          "type": "varchar(255)",
          "primaryKey": false,
          "notNull": true
        },
        "stripe_product_id": {
          "name": "stripe_product_id",
          "type": "varchar(255)",
          "primaryKey": false,
          "notNull": true
        },
        "plan": {
          "name": "plan",
          "type": "sample_plan",
          "typeSchema": "public",
          "primaryKey": false,
          "notNull": true
        },
        "status": {
          "name": "status",
          "type": "sample_subscription_status",
          "typeSchema": "public",
          "primaryKey": false,
          "notNull": true
        },
        "billing_cycle": {
          "name": "billing_cycle",
          "type": "sample_billing_cycle",
          "typeSchema": "public",
          "primaryKey": false,
          "notNull": true
        },
        "current_period_start": {
          "name": "current_period_start",
          "type": "timestamp",
          "primaryKey": false,
          "notNull": true
        },
        "current_period_end": {
          "name": "current_period_end",
          "type": "timestamp",
          "primaryKey": false,
          "notNull": true
        },
        "cancel_at": {
          "name": "cancel_at",
          "type": "timestamp",
          "primaryKey": false,
          "notNull": false
        },
        "canceled_at": {
          "name": "canceled_at",
          "type": "timestamp",
          "primaryKey": false,
          "notNull": false
        },
        "cancel_reason": {
          "name": "cancel_reason",
          "type": "text",
          "primaryKey": false,
          "notNull": false
        },
        "trial_start": {
          "name": "trial_start",
          "type": "timestamp",
          "primaryKey": false,
          "notNull": false
        },
        "trial_end": {
          "name": "trial_end",
          "type": "timestamp",
          "primaryKey": false,
          "notNull": false
        },
        "created_at": {
          "name": "created_at",
          "type": "timestamp",
          "primaryKey": false,
          "notNull": true,
          "default": "now()"
        },
        "updated_at": {
          "name": "updated_at",
          "type": "timestamp",
          "primaryKey": false,
          "notNull": true,
          "default": "now()"
        }
      },
      "indexes": {
        "sample_subscriptions_user_id_idx": {
          "name": "sample_subscriptions_user_id_idx",
          "columns": [
            {
              "expression": "user_id",
              "isExpression": false,
              "asc": true,
              "nulls": "last"
            }
          ],
          "isUnique": false,
          "concurrently": false,
          "method": "btree",
          "with": {}
        },
        "sample_subscriptions_status_idx": {
          "name": "sample_subscriptions_status_idx",
          "columns": [
            {
              "expression": "status",
              "isExpression": false,
              "asc": true,
              "nulls": "last"
            }
          ],
          "isUnique": false,
          "concurrently": false,
          "method": "btree",
          "with": {}
        },
        "sample_subscriptions_plan_idx": {
          "name": "sample_subscriptions_plan_idx",
          "columns": [
            {
              "expression": "plan",
              "isExpression": false,
              "asc": true,
              "nulls": "last"
            }
          ],
          "isUnique": false,
          "concurrently": false,
          "method": "btree",
          "with": {}
        }
      },
      "foreignKeys": {},
      "compositePrimaryKeys": {},
      "uniqueConstraints": {
        "sample_subscriptions_stripe_subscription_id_unique": {
          "name": "sample_subscriptions_stripe_subscription_id_unique",
          "nullsNotDistinct": false,
          "columns": [
            "stripe_subscription_id"
          ]
        }
      },
      "policies": {},
      "checkConstraints": {},
      "isRLSEnabled": false
    },
    "public.sample_webhook_events": {
      "name": "sample_webhook_events",
      "schema": "",
      "columns": {
        "id": {
          "name": "id",
          "type": "uuid",
          "primaryKey": true,
          "notNull": true,
          "default": "gen_random_uuid()"
        },
        "stripe_event_id": {
          "name": "stripe_event_id",
          "type": "varchar(255)",
          "primaryKey": false,
          "notNull": true
        },
        "event_type": {
          "name": "event_type",
          "type": "varchar(100)",
          "primaryKey": false,
          "notNull": true
        },
        "api_version": {
          "name": "api_version",
          "type": "varchar(50)",
          "primaryKey": false,
          "notNull": false
        },
        "payload": {
          "name": "payload",
          "type": "jsonb",
          "primaryKey": false,
          "notNull": true
        },
        "object_id": {
          "name": "object_id",
          "type": "varchar(255)",
          "primaryKey": false,
          "notNull": false
        },
        "object_type": {
          "name": "object_type",
          "type": "varchar(50)",
          "primaryKey": false,
          "notNull": false
        },
        "status": {
          "name": "status",
          "type": "sample_webhook_status",
          "typeSchema": "public",
          "primaryKey": false,
          "notNull": true,
          "default": "'pending'"
        },
        "processed_at": {
          "name": "processed_at",
          "type": "timestamp",
          "primaryKey": false,
          "notNull": false
        },
        "failure_reason": {
          "name": "failure_reason",
          "type": "text",
          "primaryKey": false,
          "notNull": false
        },
        "retry_count": {
          "name": "retry_count",
          "type": "integer",
          "primaryKey": false,
          "notNull": false,
          "default": 0
        },
        "event_created_at": {
          "name": "event_created_at",
          "type": "timestamp",
          "primaryKey": false,
          "notNull": true
        },
        "created_at": {
          "name": "created_at",
          "type": "timestamp",
          "primaryKey": false,
          "notNull": true,
          "default": "now()"
        }
      },
      "indexes": {
        "sample_webhook_events_event_type_idx": {
          "name": "sample_webhook_events_event_type_idx",
          "columns": [
            {
              "expression": "event_type",
              "isExpression": false,
              "asc": true,
              "nulls": "last"
            }
          ],
          "isUnique": false,
          "concurrently": false,
          "method": "btree",
          "with": {}
        },
        "sample_webhook_events_status_idx": {
          "name": "sample_webhook_events_status_idx",
          "columns": [
            {
              "expression": "status",
              "isExpression": false,
              "asc": true,
              "nulls": "last"
            }
          ],
          "isUnique": false,
          "concurrently": false,
          "method": "btree",
          "with": {}
        },
        "sample_webhook_events_object_id_idx": {
          "name": "sample_webhook_events_object_id_idx",
          "columns": [
            {
              "expression": "object_id",
              "isExpression": false,
              "asc": true,
              "nulls": "last"
            }
          ],
          "isUnique": false,
          "concurrently": false,
          "method": "btree",
          "with": {}
        }
      },
      "foreignKeys": {},
      "compositePrimaryKeys": {},
      "uniqueConstraints": {
        "sample_webhook_events_stripe_event_id_unique": {
          "name": "sample_webhook_events_stripe_event_id_unique",
          "nullsNotDistinct": false,
          "columns": [
            "stripe_event_id"
          ]
        }
      },
      "policies": {},
      "checkConstraints": {},
      "isRLSEnabled": false
    }
  },
  "enums": {
    "public.sample_billing_cycle": {
      "name": "sample_billing_cycle",
      "schema": "public",
      "values": [
        "monthly",
        "yearly"
      ]
    },
    "public.sample_payment_status": {
      "name": "sample_payment_status",
      "schema": "public",
      "values": [
        "paid",
        "failed",
        "pending",
        "refunded"
      ]
    },
    "public.sample_plan": {
      "name": "sample_plan",
      "schema": "public",
      "values": [
        "free",
        "indie",
        "pro"
      ]
    },
    "public.sample_project_status": {
      "name": "sample_project_status",
      "schema": "public",
      "values": [
        "active",
        "archived",
        "completed"
      ]
    },
    "public.sample_subscription_status": {
      "name": "sample_subscription_status",
      "schema": "public",
      "values": [
        "active",
        "past_due",
        "canceled",
        "unpaid"
      ]
    },
    "public.sample_webhook_status": {
      "name": "sample_webhook_status",
      "schema": "public",
      "values": [
        "pending",
        "processed",
        "failed"
      ]
    }
  },
  "schemas": {},
  "sequences": {},
  "roles": {},
  "policies": {},
  "views": {},
  "_meta": {
    "columns": {},
    "schemas": {},
    "tables": {}
  }
}